iris/__init__.py
iris/data.py
iris/planning.py
iris/_tests/__init__.py
iris/_tests/test_data.py
iris/_tests/test_planning.py
iris/sg/__init__.py
iris/sg/_effective_area.py
iris/sg/_effective_area_test.py
iris/sg/_sg.py
iris/sg/_sg_test.py
iris/sg/_spectrograph.py
iris/sg/_spectrograph_test.py
iris/sg/background/__init__.py
iris/sg/background/_background.py
iris/sg/background/_background_test.py
interface_region_imaging_spectrograph-0.8.0.dist-info/METADATA
interface_region_imaging_spectrograph-0.8.0.dist-info/WHEEL
interface_region_imaging_spectrograph-0.8.0.dist-info/top_level.txt
interface_region_imaging_spectrograph-0.8.0.dist-info/RECORD
